tritonllm/README.md
tritonllm/__init__.py
tritonllm/utils.py
tritonllm/bin/prompt.txt
tritonllm/bin/prompt_zh.txt
tritonllm/entrypoints/__init__.py
tritonllm/entrypoints/cli.py
tritonllm/gpt_oss/__init__.py
tritonllm/gpt_oss/bench.py
tritonllm/gpt_oss/chat.py
tritonllm/gpt_oss/generate.py
tritonllm/gpt_oss/tokenizer.py
tritonllm/gpt_oss/responses_api/__init__.py
tritonllm/gpt_oss/responses_api/api_server.py
tritonllm/gpt_oss/responses_api/events.py
tritonllm/gpt_oss/responses_api/serve.py
tritonllm/gpt_oss/responses_api/types.py
tritonllm/gpt_oss/responses_api/utils.py
tritonllm/gpt_oss/responses_api/inference/__init__.py
tritonllm/gpt_oss/responses_api/inference/stub.py
tritonllm/gpt_oss/responses_api/inference/triton.py
tritonllm/gpt_oss/tools/__init__.py
tritonllm/gpt_oss/tools/apply_patch.py
tritonllm/gpt_oss/tools/tool.py
tritonllm/gpt_oss/tools/python_docker/docker_tool.py
tritonllm/gpt_oss/tools/simple_browser/__init__.py
tritonllm/gpt_oss/tools/simple_browser/backend.py
tritonllm/gpt_oss/tools/simple_browser/page_contents.py
tritonllm/gpt_oss/tools/simple_browser/simple_browser_tool.py
tritonllm/gpt_oss/triton/__init__.py
tritonllm/gpt_oss/triton/attention.py
tritonllm/gpt_oss/triton/attention_with_tma.py
tritonllm/gpt_oss/triton/model.py
tritonllm/gpt_oss/triton/moe.py
tritonllm/gpt_oss/triton/triton_kernels.py
tritonllm/gpt_oss/triton/weights.py
tritonllm/triton_kernels/__init__.py
tritonllm/triton_kernels/compaction.py
tritonllm/triton_kernels/matmul_ogs.py
tritonllm/triton_kernels/numerics.py
tritonllm/triton_kernels/proton_opts.py
tritonllm/triton_kernels/routing.py
tritonllm/triton_kernels/specialize.py
tritonllm/triton_kernels/swiglu.py
tritonllm/triton_kernels/target_info.py
tritonllm/triton_kernels/tensor.py
tritonllm/triton_kernels/testing.py
tritonllm/triton_kernels/topk.py
tritonllm/triton_kernels/compaction_details/_masked_compaction.py
tritonllm/triton_kernels/matmul_ogs_details/_common.py
tritonllm-0.1.0.dist-info/licenses/LICENSE
tritonllm-0.1.0.dist-info/METADATA
tritonllm-0.1.0.dist-info/WHEEL
tritonllm-0.1.0.dist-info/entry_points.txt
tritonllm-0.1.0.dist-info/top_level.txt
tritonllm-0.1.0.dist-info/RECORD
