Metadata-Version: 2.4
Name: tritonllm
Version: 0.1.0
Summary: Flexible and modular LLM inference for mini-batch
Author-email: Bob Huang <git@bobhuang.xyz>
License-Expression: MIT
Project-URL: repository, https://github.com/OpenMLIR/TritonLLM
Project-URL: homepage, https://tritonllm.top
Requires-Python: <3.14,>=3.11
License-File: LICENSE
Requires-Dist: openai-harmony
Requires-Dist: tiktoken>=0.9.0
Requires-Dist: aiohttp>=3.12.14
Requires-Dist: chz>=0.3.0
Requires-Dist: docker>=7.1.0
Requires-Dist: fastapi>=0.116.1
Requires-Dist: html2text>=2025.4.15
Requires-Dist: lxml>=4.9.4
Requires-Dist: pydantic>=2.11.7
Requires-Dist: structlog>=25.4.0
Requires-Dist: tenacity>=9.1.2
Requires-Dist: uvicorn>=0.35.0
Requires-Dist: requests>=2.31.0
Requires-Dist: termcolor
Requires-Dist: torch>=2.7.0
Requires-Dist: triton==3.4.0
Requires-Dist: safetensors>=0.5.3
Requires-Dist: pytest>=8.4.1
Requires-Dist: modelscope>=1.29.0
Requires-Dist: numpy>=2.3.2
Dynamic: license-file
